raspc_notif/__init__.py
raspc_notif/notif.py
raspc_notif/raspc_notif_lib3_arm64_ssl1.1.1.so
raspc_notif/raspc_notif_lib3_arm64_ssl3.0.11.so
raspc_notif/raspc_notif_lib3_armhf_ssl1.1.1.so
raspc_notif/raspc_notif_lib3_armhf_ssl3.0.11.so
raspc_notif-1.1.1.dist-info/licenses/LICENSE
raspc_notif-1.1.1.dist-info/METADATA
raspc_notif-1.1.1.dist-info/WHEEL
raspc_notif-1.1.1.dist-info/top_level.txt
raspc_notif-1.1.1.dist-info/RECORD
