Metadata-Version: 2.4
Name: raspc_notif
Version: 1.1.1
Summary: RaspController notifications
Author-email: Ettore Gallina <info@egalnetsoftwares.com>
License-Expression: LicenseRef-Proprietary
Project-URL: Homepage, https://www.egalnetsoftwares.com
Project-URL: Documentation, https://www.egalnetsoftwares.com/files/raspcontroller/raspc_notif_lib_docs/
Keywords: RaspController,notifications,Raspberry Pi
Classifier: Programming Language :: Python :: 3
Classifier: Operating System :: Unix
Requires-Python: >=3.6
License-File: LICENSE
Dynamic: license-file
